dummytools/__init__.py
dummytools/converter.py
dummytools-0.1.0.dist-info/licenses/LICENSE
tests/__init__.py
tests/test_converter.py
dummytools-0.1.0.dist-info/METADATA
dummytools-0.1.0.dist-info/WHEEL
dummytools-0.1.0.dist-info/top_level.txt
dummytools-0.1.0.dist-info/RECORD
