Metadata-Version: 2.4
Name: dummytools
Version: 0.1.0
Summary: A dummy Python package for learning packaging
Author: diogohs
License: MIT License
Project-URL: Homepage, https://github.com/diogohs/dummytools
Project-URL: Repository, https://github.com/diogohs/dummytools
Project-URL: Issues, https://github.com/diogohs/dummytools/issues
Requires-Python: >=3.7
License-File: LICENSE
Dynamic: license-file
